noise3d/__init__.py
noise3d/_version.py
noise3d/bias.py
noise3d/disp.py
noise3d/genseq.py
noise3d/noise.py
noise3d/opr.py
noise3d/readseq.py
noise3d/spectrum.py
noise3d/stats.py
noise3d-0.0.2.dist-info/METADATA
noise3d-0.0.2.dist-info/RECORD
noise3d-0.0.2.dist-info/WHEEL
noise3d-0.0.2.dist-info/top_level.txt
