Metadata-Version: 2.1
Name: noise3d
Version: 0.0.2
Summary: Noise analysis based on 3D noise model
Home-page: https://github.com/mocquin/noise3d
Author: mocquin
Author-email: mocquin@me.com
License: MIT
Keywords: noise 3Dnoise
Platform: UNKNOWN
Requires-Dist: numpy
Requires-Dist: scipy
Requires-Dist: matplotlib
